djangocms_static_ace/__init__.py
djangocms_static_ace/static/admin/vendor/ace/ace.js
djangocms_static_ace/static/admin/vendor/ace/ext-beautify.js
djangocms_static_ace/static/admin/vendor/ace/ext-code_lens.js
djangocms_static_ace/static/admin/vendor/ace/ext-elastic_tabstops_lite.js
djangocms_static_ace/static/admin/vendor/ace/ext-emmet.js
djangocms_static_ace/static/admin/vendor/ace/ext-error_marker.js
djangocms_static_ace/static/admin/vendor/ace/ext-hardwrap.js
djangocms_static_ace/static/admin/vendor/ace/ext-keybinding_menu.js
djangocms_static_ace/static/admin/vendor/ace/ext-language_tools.js
djangocms_static_ace/static/admin/vendor/ace/ext-linking.js
djangocms_static_ace/static/admin/vendor/ace/ext-modelist.js
djangocms_static_ace/static/admin/vendor/ace/ext-options.js
djangocms_static_ace/static/admin/vendor/ace/ext-prompt.js
djangocms_static_ace/static/admin/vendor/ace/ext-rtl.js
djangocms_static_ace/static/admin/vendor/ace/ext-searchbox.js
djangocms_static_ace/static/admin/vendor/ace/ext-settings_menu.js
djangocms_static_ace/static/admin/vendor/ace/ext-spellcheck.js
djangocms_static_ace/static/admin/vendor/ace/ext-split.js
djangocms_static_ace/static/admin/vendor/ace/ext-static_highlight.js
djangocms_static_ace/static/admin/vendor/ace/ext-statusbar.js
djangocms_static_ace/static/admin/vendor/ace/ext-textarea.js
djangocms_static_ace/static/admin/vendor/ace/ext-themelist.js
djangocms_static_ace/static/admin/vendor/ace/ext-whitespace.js
djangocms_static_ace/static/admin/vendor/ace/keybinding-emacs.js
djangocms_static_ace/static/admin/vendor/ace/keybinding-sublime.js
djangocms_static_ace/static/admin/vendor/ace/keybinding-vim.js
djangocms_static_ace/static/admin/vendor/ace/keybinding-vscode.js
djangocms_static_ace/static/admin/vendor/ace/mode-abap.js
djangocms_static_ace/static/admin/vendor/ace/mode-abc.js
djangocms_static_ace/static/admin/vendor/ace/mode-actionscript.js
djangocms_static_ace/static/admin/vendor/ace/mode-ada.js
djangocms_static_ace-1.1.0.dist-info/LICENSE
djangocms_static_ace-1.1.0.dist-info/METADATA
djangocms_static_ace-1.1.0.dist-info/WHEEL
djangocms_static_ace-1.1.0.dist-info/top_level.txt
djangocms_static_ace-1.1.0.dist-info/RECORD
