Metadata-Version: 2.1
Name: djangocms-static-ace
Version: 1.1.0
Summary: Adds ace 1.9.6 to static files.
Home-page: https://github.com/fsbraun/djangocms-frontend
Author: fsbraun
Author-email: fsbraun@gmx.de
License: MIT license
Classifier: Development Status :: 5 - Production/Stable
Classifier: Environment :: Web Environment
Classifier: Intended Audience :: Developers
Classifier: License :: OSI Approved :: BSD License
Classifier: Operating System :: OS Independent
Classifier: Programming Language :: Python
Classifier: Framework :: Django
Classifier: Topic :: Internet :: WWW/HTTP
Classifier: Topic :: Internet :: WWW/HTTP :: Dynamic Content
Classifier: Topic :: Software Development
Classifier: Topic :: Software Development :: Libraries
License-File: LICENSE
Requires-Dist: Django
